zepid/__init__.py
zepid/base.py
zepid/version.py
zepid/calc/__init__.py
zepid/calc/utils.py
zepid/causal/__init__.py
zepid/causal/utils.py
zepid/causal/causalgraph/__init__.py
zepid/causal/causalgraph/dag.py
zepid/causal/doublyrobust/AIPW.py
zepid/causal/doublyrobust/TMLE.py
zepid/causal/doublyrobust/__init__.py
zepid/causal/doublyrobust/crossfit.py
zepid/causal/doublyrobust/utils.py
zepid/causal/generalize/__init__.py
zepid/causal/generalize/estimators.py
zepid/causal/gformula/TimeFixed.py
zepid/causal/gformula/TimeVary.py
zepid/causal/gformula/__init__.py
zepid/causal/ipw/IPCW.py
zepid/causal/ipw/IPMW.py
zepid/causal/ipw/IPTW.py
zepid/causal/ipw/__init__.py
zepid/causal/snm/__init__.py
zepid/causal/snm/g_estimation.py
zepid/datasets/__init__.py
zepid/datasets/binge.dat
zepid/datasets/case_control.dat
zepid/datasets/data.dat
zepid/datasets/ewing.dat
zepid/datasets/generalize_conf.dat
zepid/datasets/generalize_rct.dat
zepid/datasets/gvhd.dat
zepid/datasets/leukemia.dat
zepid/datasets/longitudinal.dat
zepid/datasets/monotone.dat
zepid/datasets/sciatica.dat
zepid/datasets/zivich_breskin_sim.csv
zepid/graphics/__init__.py
zepid/graphics/graphics.py
zepid/sensitivity_analysis/Simple.py
zepid/sensitivity_analysis/__init__.py
zepid/sensitivity_analysis/distributions.py
zepid/superlearner/__init__.py
zepid/superlearner/estimators.py
zepid/superlearner/stackers.py
zepid-0.9.1.dist-info/LICENSE.txt
zepid-0.9.1.dist-info/METADATA
zepid-0.9.1.dist-info/WHEEL
zepid-0.9.1.dist-info/top_level.txt
zepid-0.9.1.dist-info/RECORD
