Metadata-Version: 2.1
Name: zepid
Version: 0.9.1
Summary: Tool package for epidemiologic analyses
Home-page: https://github.com/pzivich/zepid
Author: Paul Zivich
Author-email: zepidpy@gmail.com
License: MIT
Keywords: epidemiology inverse-probability-weights risk-ratio g-computation g-formula IPW AIPW TMLE
Platform: UNKNOWN
Classifier: Programming Language :: Python :: 3.6
Classifier: Programming Language :: Python :: 3.7
Classifier: Programming Language :: Python :: 3.8
Classifier: Programming Language :: Python :: 3.9
Classifier: Programming Language :: Python :: 3.10
License-File: LICENSE.txt
Requires-Dist: pandas (>=0.18)
Requires-Dist: numpy
Requires-Dist: statsmodels (>=0.7.0)
Requires-Dist: matplotlib (>=2.0)
Requires-Dist: scipy
Requires-Dist: tabulate
Requires-Dist: scikit-learn
Requires-Dist: patsy
Provides-Extra: directedacyclicgraph
Requires-Dist: networkx ; extra == 'directedacyclicgraph'
